tempproj/__init__.py
tempproj/test.py
tempproj/supervised_classification/__init__.py
tempproj/supervised_classification/_classification.py
tempproj/supervised_classification/_regression.py
tempproj/supervised_classification/_regression_0603.py
tempproj-4.1.0.dist-info/LICENSE
tempproj-4.1.0.dist-info/METADATA
tempproj-4.1.0.dist-info/WHEEL
tempproj-4.1.0.dist-info/top_level.txt
tempproj-4.1.0.dist-info/RECORD
